MANIFEST.in
README.md
setup.py
chargehound/__init__.py
chargehound/api_requestor.py
chargehound/error.py
chargehound/models.py
chargehound/resources.py
chargehound/version.py
chargehound.egg-info/PKG-INFO
chargehound.egg-info/SOURCES.txt
chargehound.egg-info/dependency_links.txt
chargehound.egg-info/requires.txt
chargehound.egg-info/top_level.txt
test/test_chargehound.py
test/test_disputes.py
test/test_error.py
test/test_requestor.py