Metadata-Version: 1.0
Name: chargehound
Version: 2.3.2
Summary: Chargehound Python Bindings
Home-page: https://www.chargehound.com
Author: Chargehound
Author-email: support@chargehound.com
License: MIT
Platform: UNKNOWN
